setup.py
pings/__init__.py
pings/consts.py
pings/ping.py
pings/response.py
pings.egg-info/PKG-INFO
pings.egg-info/SOURCES.txt
pings.egg-info/dependency_links.txt
pings.egg-info/top_level.txt